<?xml version="1.0" encoding="UTF-8"?>
<elements source="Harmony Premium (HarmonyPremium.exe) version 15.0.5 build 13929 2018-08-13 08:19:50" version="1505" build="13929">
 <element id="1" elementName="Head" elementFolder="Head" pixmapFormat="2" scanType="2" fieldChart="12" vectorType="2" rootFolder="elements"/>
 <element id="9" elementName="Body" elementFolder="Body" pixmapFormat="2" scanType="2" fieldChart="12" vectorType="2" rootFolder="elements"/>
 <element id="10" elementName="Left_Foot" elementFolder="Left_Foot" pixmapFormat="2" scanType="2" fieldChart="12" vectorType="2" rootFolder="elements"/>
 <element id="11" elementName="Right_Foot" elementFolder="Right_Foot" pixmapFormat="2" scanType="2" fieldChart="12" vectorType="2" rootFolder="elements"/>
 <element id="12" elementName="Left_Arm" elementFolder="Left_Arm" pixmapFormat="2" scanType="2" fieldChart="12" vectorType="2" rootFolder="elements"/>
 <element id="13" elementName="Right_Arm" elementFolder="Right_Arm" pixmapFormat="2" scanType="2" fieldChart="12" vectorType="2" rootFolder="elements"/>
 <element id="14" elementName="Hair_Top_Back_SIDE" elementFolder="Hair_Top_Back_SIDE" pixmapFormat="2" scanType="2" fieldChart="12" vectorType="2" rootFolder="elements"/>
 <element id="15" elementName="Left_Eye" elementFolder="Left_Eye" pixmapFormat="2" scanType="2" fieldChart="12" vectorType="2" rootFolder="elements"/>
 <element id="16" elementName="Right_Eye" elementFolder="Right_Eye" pixmapFormat="2" scanType="2" fieldChart="12" vectorType="2" rootFolder="elements"/>
 <element id="17" elementName="Brow" elementFolder="Brow" pixmapFormat="2" scanType="2" fieldChart="12" vectorType="2" rootFolder="elements"/>
 <element id="18" elementName="Hair_Leaves_L" elementFolder="Hair_Leaves_L" pixmapFormat="2" scanType="2" fieldChart="12" vectorType="2" rootFolder="elements"/>
 <element id="19" elementName="Head_Leave_R" elementFolder="Head_Leave_R" pixmapFormat="2" scanType="2" fieldChart="12" vectorType="2" rootFolder="elements"/>
 <element id="20" elementName="Reference_Lines" elementFolder="Reference_Lines" pixmapFormat="2" scanType="2" fieldChart="12" vectorType="2" rootFolder="elements"/>
 <element id="21" elementName="Back_Hair_L" elementFolder="Back_Hair_L" pixmapFormat="2" scanType="2" fieldChart="12" vectorType="2" rootFolder="elements"/>
 <element id="22" elementName="Back_Hair_R" elementFolder="Back_Hair_R" pixmapFormat="2" scanType="2" fieldChart="12" vectorType="2" rootFolder="elements"/>
 <element id="23" elementName="Side_Arm" elementFolder="Side_Arm" pixmapFormat="2" scanType="2" fieldChart="12" vectorType="2" rootFolder="elements"/>
 <element id="25" elementName="Side_Arm" elementFolder="Side_Arm.25" pixmapFormat="2" scanType="2" fieldChart="12" vectorType="2" rootFolder="elements"/>
</elements>
